[
  { "time": 0.000, "text": "Oh baby, oh" },
  { "time": 3.079, "text": "Oh baby, oh" },
  { "time": 4.837, "text": "Uhmm" },
  { "time": 5.495, "text": "Oh baby, oh" },
  { "time": 7.740, "text": "Oh baby, oh" },
  { "time": 10.155, "text": "Oh baby, oh" },
  { "time": 12.461, "text": "Oh baby, oh" },
  { "time": 14.880, "text": "Oh baby, oh" },
  { "time": 17.104, "text": "Oh baby, oh" },
  { "time": 19.508, "text": "Oh baby, oh" },
  { "time": 21.805, "text": "Oh baby, oh" },
  { "time": 24.241, "text": "Oh baby, oh" },
  { "time": 26.567, "text": "Oh baby, oh" },
  { "time": 28.917, "text": "Oh baby, oh" },
  { "time": 31.223, "text": "Oh baby, oh" },
  { "time": 33.643, "text": "Oh baby, oh" },
  { "time": 35.915, "text": "Oh baby, oh" },
  { "time": 38.384, "text": "Oh baby, oh" },
  { "time": 40.620, "text": "Oh baby, oh" },
  { "time": 43.068, "text": "Oh baby, oh" },
  { "time": 45.345, "text": "Oh baby, oh" },
  { "time": 47.773, "text": "Oh baby, oh" },
  { "time": 50.111, "text": "Oh baby, oh" },
  { "time": 52.466, "text": "Oh baby, oh" },
  { "time": 54.695, "text": "Oh baby, oh" },
  { "time": 57.109, "text": "Oh baby, oh" },
  { "time": 59.448, "text": "Oh baby, oh" },
  { "time": 61.908, "text": "Oh baby, oh" },
  { "time": 64.206, "text": "Oh baby, oh" },
  { "time": 66.580, "text": "Oh baby, oh" },
  { "time": 68.934, "text": "Oh baby, oh" },
  { "time": 71.345, "text": "Oh baby, oh" },
  { "time": 73.720, "text": "Oh baby, oh" },
  { "time": 76.022, "text": "Oh baby, oh" },
  { "time": 78.316, "text": "Oh baby, oh" },
  { "time": 80.669, "text": "Oh baby, oh" },
  { "time": 83.069, "text": "Oh baby, oh" },
  { "time": 85.314, "text": "Oh baby, oh" },
  { "time": 87.714, "text": "Oh baby, oh" },
  { "time": 90.052, "text": "Oh baby, oh" },
  { "time": 92.358, "text": "Oh baby, oh" },
  { "time": 94.740, "text": "Oh baby, oh" },
  { "time": 97.050, "text": "Oh baby, oh" },
  { "time": 99.494, "text": "Oh baby, oh" },
  { "time": 101.816, "text": "Oh baby, oh" },
  { "time": 104.154, "text": "Oh baby, oh" },
  { "time": 106.524, "text": "Oh baby, oh" },
  { "time": 108.935, "text": "Oh baby, oh" },
  { "time": 111.274, "text": "Oh baby, oh" },
  { "time": 113.690, "text": "Oh baby, oh" },
  { "time": 116.280, "text": "Baby" },
  { "time": 120.112, "text": "Believe in me" },
  { "time": 122.970, "text": "Yeah baby" },
  { "time": 127.111, "text": "Oh baby" },
  { "time": 132.505, "text": "Important to me" },
  { "time": 136.678, "text": "Important to me" },
  { "time": 140.129, "text": "Important to me" },
  { "time": 141.841, "text": "Important to me" },
  { "time": 144.540, "text": "Yeah baby" },
  { "time": 146.636, "text": "Important to me" },
  { "time": 148.763, "text": "To me" },
  { "time": 151.360, "text": "Important to me" },
  { "time": 153.666, "text": "Important to me" },
  { "time": 155.879, "text": "Important to me" },
  { "time": 158.157, "text": "Important to me" },
  { "time": 160.649, "text": "Important to me" },
  { "time": 162.954, "text": "Important to me" },
  { "time": 165.326, "text": "Important to me" },
  { "time": 167.569, "text": "Important to me" },
  { "time": 169.279, "text": "Yeah baby" },
  { "time": 170.229, "text": "Oh baby, oh" },
  { "time": 172.429, "text": "Oh baby, oh" },
  { "time": 174.840, "text": "Oh baby, oh" },
  { "time": 177.117, "text": "Oh baby, oh" },
  { "time": 179.549, "text": "Oh baby, oh" },
  { "time": 181.795, "text": "Oh baby, oh" },
  { "time": 184.226, "text": "Oh baby, oh" },
  { "time": 187.323, "text": "Oh baby, oh" },
  { "time": 188.958, "text": "Oh" }
]